{
	"pages": [{
		"path": "pages/index/index",
		"style": {
			"navigationBarTitleText": "九云商城"
		}
	}    ,{
            "path" : "pages/cate/cate",
            "style" :                                                                                    
            {
                "navigationBarTitleText": "",
                "enablePullDownRefresh": false
            }
            
        }
        ,{
            "path" : "pages/my/my",
            "style" :                                                                                    
            {
                "navigationBarTitleText": "",
                "enablePullDownRefresh": false
            }
            
        }
        ,{
            "path" : "pages/cart/cart",
            "style" :                                                                                    
            {
                "navigationBarTitleText": "",
                "enablePullDownRefresh": false
            }
            
        }
    ],
	// 子包目录
	"subPackages": [
		{
			"root": "subpkg",
			"pages": [
				{
                    "path" : "goods_detail/goods_detail",
                    "style" :                                                                                    
                {
                    "navigationBarTitleText": "",
                    "enablePullDownRefresh": false
                }
                
                }
                ,{
                    "path" : "goods_list/goods_list",
                    "style" :                                                                                     
                {
                    "navigationBarTitleText": "",
                    "enablePullDownRefresh": true,
					"onReachBottomDistance": 150
                }
                
                }
            ]
		}
	],
	"tabBar": {
		"selectedColor": "#C00000",
		"list": [
			{
				"pagePath": "pages/index/index",
				"text": "首页",
				"iconPath": "static/icons/home.png",
				"selectedIconPath": "static/icons/home-o.png"
			},
			{
				"pagePath": "pages/cate/cate",
				"text": "分类",
				"iconPath": "static/icons/category.png",
				"selectedIconPath": "static/icons/category-o.png"
			},
			{
				"pagePath": "pages/cart/cart",
				"text": "购物车",
				"iconPath": "static/icons/cart.png",
				"selectedIconPath": "static/icons/cart-o.png"
			},
			{
				"pagePath": "pages/my/my",
				"text": "我的",
				"iconPath": "static/icons/my.png",
				"selectedIconPath": "static/icons/my-o.png"
			}
		]
	},
	"globalStyle": {
		"navigationBarTextStyle": "black",
		"navigationBarTitleText": "九云商城",
		"navigationBarBackgroundColor": "#aaff7f",
		"backgroundColor": "#F8F8F8",
		"app-plus": {
			"background": "#efeff4"
		}
	}
}
